{
  "_class": "symbolInstance",
  "booleanOperation": -1,
  "clippingMaskMode": 0,
  "do_objectID": "79C4DF67-C007-4FBE-9906-533EFFB4AE6A",
  "exportOptions": {
    "_class": "exportOptions",
    "do_objectID": "7B4966DA-35B1-4E9F-821A-96326E974D20",
    "exportFormats": [
    ],
    "includedLayerIds": [
    ],
    "layerOptions": 0,
    "shouldTrim": false
  },
  "frame": {
    "_class": "rect",
    "constrainProportions": false,
    "do_objectID": "E6E378E8-71CF-44DC-8705-20D8E088BFDA",
    "height": 50,
    "width": 333,
    "x": 0,
    "y": 273
  },
  "hasClippingMask": false,
  "horizontalSpacing": 0,
  "isFixedToViewport": false,
  "isFlippedHorizontal": false,
  "isFlippedVertical": false,
  "isLocked": false,
  "isVisible": true,
  "layerListExpandedType": 0,
  "name": "Lists/Detail/Default",
  "nameIsFixed": false,
  "overrideValues": [
    {
      "_class": "overrideValue",
      "overrideName": "01ADC331-A0AF-48C8-99B9-2345D9D9B2F2_stringValue",
      "value": "Gutter on outside"
    },
    {
      "_class": "overrideValue",
      "overrideName": "D9B110FF-3431-45A5-9B7B-8C3A72496BB9_stringValue",
      "value": "Yes"
    },
    {
      "_class": "overrideValue",
      "overrideName": "4D15C026-A365-42BE-ACB3-DEE5C2037DBD_symbolID",
      "value": ""
    }
  ],
  "resizingConstraint": 47,
  "resizingType": 0,
  "rotation": 0,
  "scale": 1,
  "shouldBreakMaskChain": false,
  "style": {
    "_class": "style",
    "do_objectID": "AEE2D7E7-75EE-4E56-8832-8775EFE37A48",
    "endMarkerType": 0,
    "miterLimit": 10,
    "startMarkerType": 0,
    "windingRule": 1
  },
  "symbolID": "293A07D6-4B74-4F8F-9B1A-105BC6588DA4",
  "userInfo": {
    "com.animaapp.stc-sketch-plugin": {
      "kModelPropertiesKey": {
      }
    }
  },
  "verticalSpacing": 0
}