{
  "_class": "symbolInstance",
  "booleanOperation": 0,
  "clippingMaskMode": 0,
  "do_objectID": "84705446-F187-4155-ADB7-5727B500D32B",
  "exportOptions": {
    "_class": "exportOptions",
    "do_objectID": "E1F71862-8909-4C40-A798-9EF2ED88521B",
    "exportFormats": [
    ],
    "includedLayerIds": [
    ],
    "layerOptions": 0,
    "shouldTrim": false
  },
  "frame": {
    "_class": "rect",
    "constrainProportions": false,
    "do_objectID": "CA239E85-2F45-4D76-8318-C10CF4E8150E",
    "height": 48,
    "width": 241,
    "x": 0,
    "y": 192
  },
  "hasClippingMask": false,
  "horizontalSpacing": 0,
  "isFixedToViewport": false,
  "isFlippedHorizontal": false,
  "isFlippedVertical": false,
  "isLocked": false,
  "isVisible": true,
  "layerListExpandedType": 0,
  "name": "Form group/.input-only/Error",
  "nameIsFixed": false,
  "overrideValues": [
    {
      "_class": "overrideValue",
      "do_objectID": "0C601896-2E08-41AB-8919-7395709BC5AA",
      "overrideName": "10A2066D-300C-4DD3-BAE8-4D615346000D_stringValue",
      "value": " Invalid"
    }
  ],
  "resizingConstraint": 63,
  "resizingType": 0,
  "rotation": 0,
  "scale": 1,
  "shouldBreakMaskChain": false,
  "style": {
    "_class": "style",
    "do_objectID": "9215A670-1BAA-4E66-9915-039565E9BE49",
    "endMarkerType": 0,
    "miterLimit": 10,
    "startMarkerType": 0,
    "windingRule": 1
  },
  "symbolID": "B732950D-3D14-40B0-B911-CBB737F93E78",
  "userInfo": {
    "com.animaapp.stc-sketch-plugin": {
      "kModelPropertiesKey": {
      }
    }
  },
  "verticalSpacing": 0
}