{
  "_class": "symbolInstance",
  "booleanOperation": -1,
  "clippingMaskMode": 0,
  "do_objectID": "EBEA6109-A5BF-4191-A3CA-8CFECB5ED7BA",
  "exportOptions": {
    "_class": "exportOptions",
    "do_objectID": "5BDA0BEB-2779-4998-84E6-3FFEE20560B0",
    "exportFormats": [
    ],
    "includedLayerIds": [
    ],
    "layerOptions": 0,
    "shouldTrim": false
  },
  "frame": {
    "_class": "rect",
    "constrainProportions": false,
    "do_objectID": "394A6B22-3711-4A3E-A588-103E7E074D0D",
    "height": 46.2439024390244,
    "width": 44.51640033641707,
    "x": 0.8843799644893691,
    "y": 0
  },
  "hasClippingMask": false,
  "horizontalSpacing": 0,
  "isFixedToViewport": false,
  "isFlippedHorizontal": false,
  "isFlippedVertical": false,
  "isLocked": false,
  "isVisible": true,
  "layerListExpandedType": 0,
  "name": "Date-picker/z.assets/cell-style/default",
  "nameIsFixed": false,
  "overrideValues": [
    {
      "_class": "overrideValue",
      "do_objectID": "274AB447-A8EC-42BC-A388-4AD0117113B1",
      "overrideName": "C752BA20-D4CA-4D86-AAA5-899EB8C5E32F/302F44CB-C5EE-4C5E-8FA1-FEE1784732DA_stringValue",
      "value": "1"
    }
  ],
  "resizingConstraint": 63,
  "resizingType": 0,
  "rotation": 0,
  "scale": 1,
  "shouldBreakMaskChain": false,
  "style": {
    "_class": "style",
    "do_objectID": "B14DB36C-0980-41B5-87AC-FDEEA744D0C0",
    "endMarkerType": 0,
    "miterLimit": 10,
    "startMarkerType": 0,
    "windingRule": 1
  },
  "symbolID": "65897BEE-1962-4C0F-BB8B-C1AC04E1734D",
  "userInfo": {
    "com.animaapp.stc-sketch-plugin": {
      "kModelPropertiesKey": {
      }
    }
  },
  "verticalSpacing": 0
}