{
  "_class": "group",
  "booleanOperation": -1,
  "clippingMaskMode": 0,
  "do_objectID": "D3240DEF-31F9-458E-B26E-887C4261E0CE",
  "exportOptions": {
    "_class": "exportOptions",
    "do_objectID": "1AACFFC7-227E-4491-8252-31B4CDB01918",
    "exportFormats": [
      {
        "_class": "exportFormat",
        "absoluteSize": 0,
        "fileFormat": "png",
        "name": "",
        "namingScheme": 0,
        "scale": 1,
        "visibleScaleType": 0
      }
    ],
    "includedLayerIds": [
    ],
    "layerOptions": 0,
    "shouldTrim": false
  },
  "frame": {
    "_class": "rect",
    "constrainProportions": false,
    "do_objectID": "F096A6EA-0E58-44DF-BEB8-AE8B45EB8403",
    "height": 143,
    "width": 705,
    "x": 551,
    "y": 248
  },
  "hasClickThrough": false,
  "hasClippingMask": false,
  "isFixedToViewport": false,
  "isFlippedHorizontal": false,
  "isFlippedVertical": false,
  "isLocked": false,
  "isVisible": true,
  "layerListExpandedType": 2,
  "layers": [
    {
      "class": "symbolInstance",
      "id": "C5ABA8AC-74BB-4B77-A085-34624197D864"
    },
    {
      "class": "group",
      "id": "18703CA6-BB50-4446-AE1C-B5E85175E169"
    }
  ],
  "name": "Tab/Default",
  "nameIsFixed": true,
  "resizingConstraint": 63,
  "resizingType": 0,
  "rotation": 0,
  "shouldBreakMaskChain": false,
  "style": {
    "_class": "style",
    "do_objectID": "157AF799-F2A8-40B5-9C73-3EC733B24436",
    "endMarkerType": 0,
    "miterLimit": 10,
    "startMarkerType": 0,
    "windingRule": 1
  },
  "userInfo": {
    "com.animaapp.stc-sketch-plugin": {
      "kModelPropertiesKey": {
      }
    }
  }
}