{
  "_class": "symbolInstance",
  "booleanOperation": 0,
  "clippingMaskMode": 0,
  "do_objectID": "003A8603-D549-449C-893E-01B62369F35E",
  "exportOptions": {
    "_class": "exportOptions",
    "do_objectID": "A14FF6AA-3B55-4673-9D53-F7AC89468751",
    "exportFormats": [
      {
        "_class": "exportFormat",
        "absoluteSize": 0,
        "fileFormat": "jpg",
        "name": "",
        "namingScheme": 0,
        "scale": 1,
        "visibleScaleType": 0
      }
    ],
    "includedLayerIds": [
    ],
    "layerOptions": 0,
    "shouldTrim": false
  },
  "frame": {
    "_class": "rect",
    "constrainProportions": false,
    "do_objectID": "FD89C575-B113-4B13-81A8-A521BFE47565",
    "height": 80,
    "width": 335,
    "x": 0,
    "y": 288
  },
  "hasClippingMask": false,
  "horizontalSpacing": 0,
  "isFixedToViewport": false,
  "isFlippedHorizontal": false,
  "isFlippedVertical": false,
  "isLocked": false,
  "isVisible": true,
  "layerListExpandedType": 0,
  "name": "Form group/Default",
  "nameIsFixed": false,
  "overrideValues": [
    {
      "_class": "overrideValue",
      "do_objectID": "89F9154F-876F-407E-90B2-CC65B1F2B970",
      "overrideName": "2E31709E-23A1-4616-9C55-DF71BFC26E2A_symbolID",
      "value": "8EDB0879-E266-4E4B-BE71-EA9906C95CB0"
    },
    {
      "_class": "overrideValue",
      "do_objectID": "44B20EA5-2086-4555-B7DB-21ADDACB92A1",
      "overrideName": "2E31709E-23A1-4616-9C55-DF71BFC26E2A/2D49FE73-DCEA-4C16-B6AF-AE962989E975_stringValue",
      "value": "Input hint text"
    },
    {
      "_class": "overrideValue",
      "do_objectID": "C61B28BE-9BE9-4219-85E6-4DF06CF749B2",
      "overrideName": "F6311319-AC81-42A3-98F9-1FB9FCC2130E_stringValue",
      "value": "Placeholder text"
    }
  ],
  "resizingConstraint": 63,
  "resizingType": 0,
  "rotation": 0,
  "scale": 1,
  "shouldBreakMaskChain": false,
  "style": {
    "_class": "style",
    "do_objectID": "2BE93168-F0CD-443E-B113-39738C1B4772",
    "endMarkerType": 0,
    "miterLimit": 10,
    "startMarkerType": 0,
    "windingRule": 1
  },
  "symbolID": "88E8C340-91D6-4CF3-A9DC-D84A5480E153",
  "userInfo": {
    "com.animaapp.stc-sketch-plugin": {
      "kModelPropertiesKey": {
      }
    }
  },
  "verticalSpacing": 0
}