{
  "_class": "group",
  "booleanOperation": 0,
  "clippingMaskMode": 0,
  "do_objectID": "A466D106-E329-41F4-A2EC-A1445960FDFE",
  "exportOptions": {
    "_class": "exportOptions",
    "exportFormats": [
    ],
    "includedLayerIds": [
    ],
    "layerOptions": 0,
    "shouldTrim": false
  },
  "frame": {
    "_class": "rect",
    "constrainProportions": false,
    "height": 96,
    "width": 824,
    "x": 452,
    "y": 288
  },
  "hasClickThrough": false,
  "hasClippingMask": false,
  "isFixedToViewport": false,
  "isFlippedHorizontal": false,
  "isFlippedVertical": false,
  "isLocked": false,
  "isVisible": true,
  "layerListExpandedType": 1,
  "layers": [
    {
      "class": "symbolInstance",
      "id": "C69CCD1B-B700-4259-AA33-70D906191010"
    },
    {
      "class": "symbolInstance",
      "id": "13CE7F23-6114-41C1-88D2-1AFBB0F9C569"
    },
    {
      "class": "symbolInstance",
      "id": "62E1A146-B654-4F27-8A5E-D6A026464803"
    },
    {
      "class": "symbolInstance",
      "id": "15469F76-B6C6-4DEC-AD67-865F701E6420"
    },
    {
      "class": "symbolInstance",
      "id": "7F0E67EF-3255-47AD-B91B-57BE4E73088F"
    },
    {
      "class": "symbolInstance",
      "id": "D51E8E05-C198-4FE2-878F-77FE8428B8D5"
    },
    {
      "class": "symbolInstance",
      "id": "E3B41FB7-5FB4-4C58-A755-BC4698CFC98E"
    },
    {
      "class": "symbolInstance",
      "id": "B601A0A7-8754-40D1-8430-CE623334544F"
    },
    {
      "class": "symbolInstance",
      "id": "396DE932-8ED5-4CEF-B3D3-BF8CE3A67886"
    },
    {
      "class": "symbolInstance",
      "id": "E4A6F4BE-09A2-474F-B33F-19F6903D2B9A"
    },
    {
      "class": "symbolInstance",
      "id": "9CD0E38E-0F15-4C1F-8FC6-34F0E2D1D3F9"
    }
  ],
  "name": "Stacked Group",
  "nameIsFixed": false,
  "resizingConstraint": 63,
  "resizingType": 0,
  "rotation": 0,
  "shouldBreakMaskChain": false,
  "style": {
    "_class": "style",
    "endMarkerType": 0,
    "miterLimit": 10,
    "startMarkerType": 0,
    "windingRule": 1
  },
  "userInfo": {
    "com.animaapp.stc-sketch-plugin": {
      "kModelPropertiesKey": {
        "align": 0,
        "isCollapsing": 1,
        "spacing": 36,
        "stackType": 1
      },
      "kViewTypeKey": "ADModelStackView"
    }
  }
}