{
  "_class": "group",
  "booleanOperation": -1,
  "clippingMaskMode": 0,
  "do_objectID": "6D424C3B-4A54-465E-9D68-E3695AD50726",
  "exportOptions": {
    "_class": "exportOptions",
    "do_objectID": "CCBEBCE3-4739-42C4-A2BB-57DD9C58D4F9",
    "exportFormats": [
      {
        "_class": "exportFormat",
        "absoluteSize": 0,
        "fileFormat": "png",
        "name": "",
        "namingScheme": 0,
        "scale": 1,
        "visibleScaleType": 0
      }
    ],
    "includedLayerIds": [
    ],
    "layerOptions": 0,
    "shouldTrim": false
  },
  "frame": {
    "_class": "rect",
    "constrainProportions": false,
    "do_objectID": "A924D7B6-97EF-463A-9AE9-0455D99692F4",
    "height": 48,
    "width": 347,
    "x": 0,
    "y": 0
  },
  "hasClickThrough": false,
  "hasClippingMask": false,
  "isFixedToViewport": false,
  "isFlippedHorizontal": false,
  "isFlippedVertical": false,
  "isLocked": false,
  "isVisible": true,
  "layerListExpandedType": 0,
  "layers": [
    {
      "class": "symbolInstance",
      "id": "AD7C8973-94EE-4E3B-AD56-4CA57CD43542"
    },
    {
      "class": "symbolInstance",
      "id": "6B637B9F-661D-4FC6-B599-2D99E42A5D8C"
    }
  ],
  "name": "Input Group/button-suffix [0h b]",
  "nameIsFixed": true,
  "resizingConstraint": 63,
  "resizingType": 0,
  "rotation": 0,
  "shouldBreakMaskChain": false,
  "style": {
    "_class": "style",
    "do_objectID": "D25329B9-CD38-46A3-B9FF-9ED57D4483B9",
    "endMarkerType": 0,
    "miterLimit": 10,
    "startMarkerType": 0,
    "windingRule": 1
  },
  "userInfo": {
    "com.animaapp.stc-sketch-plugin": {
      "kModelPropertiesKey": {
      }
    }
  }
}