{
  "_class": "symbolInstance",
  "booleanOperation": 0,
  "clippingMaskMode": 0,
  "do_objectID": "6482D43E-A045-4C4E-AAE9-A5454A017B7D",
  "exportOptions": {
    "_class": "exportOptions",
    "do_objectID": "AB285A62-9A7B-454D-8226-0C312757A914",
    "exportFormats": [
    ],
    "includedLayerIds": [
    ],
    "layerOptions": 0,
    "shouldTrim": false
  },
  "frame": {
    "_class": "rect",
    "constrainProportions": false,
    "do_objectID": "640E685C-AC45-430F-B606-DA6C496D8BAA",
    "height": 50,
    "width": 422,
    "x": 0,
    "y": 50
  },
  "hasClippingMask": false,
  "horizontalSpacing": 0,
  "isFixedToViewport": false,
  "isFlippedHorizontal": false,
  "isFlippedVertical": false,
  "isLocked": false,
  "isVisible": true,
  "layerListExpandedType": 0,
  "name": "Accordion/Text-area",
  "nameIsFixed": true,
  "overrideValues": [
    {
      "_class": "overrideValue",
      "do_objectID": "46EAB913-3712-492B-9C48-8F31E755369A",
      "overrideName": "5F0122B8-7389-49E2-A56E-83C76E959EBD_stringValue",
      "value": "Content here"
    }
  ],
  "resizingConstraint": 63,
  "resizingType": 0,
  "rotation": 0,
  "scale": 1,
  "shouldBreakMaskChain": false,
  "style": {
    "_class": "style",
    "do_objectID": "8BE2DDD6-2C5B-4533-8AA0-820AD47B1F3F",
    "endMarkerType": 0,
    "miterLimit": 10,
    "startMarkerType": 0,
    "windingRule": 1
  },
  "symbolID": "698419D3-A9DE-4CBC-B596-25D7A5D17E50",
  "userInfo": {
    "com.animaapp.stc-sketch-plugin": {
      "kModelPropertiesKey": {
      }
    }
  },
  "verticalSpacing": 0
}