{
  "_class": "symbolInstance",
  "booleanOperation": 0,
  "clippingMaskMode": 0,
  "do_objectID": "F432BB85-4BE9-49E8-B813-BCF0867A602C",
  "exportOptions": {
    "_class": "exportOptions",
    "do_objectID": "7333006B-20EE-4C6B-8F0D-2BC6BD874D75",
    "exportFormats": [
    ],
    "includedLayerIds": [
    ],
    "layerOptions": 0,
    "shouldTrim": false
  },
  "frame": {
    "_class": "rect",
    "constrainProportions": false,
    "do_objectID": "93058974-28A4-4DE3-950E-19B9EBAA41D1",
    "height": 50,
    "width": 386,
    "x": 0,
    "y": 139
  },
  "hasClippingMask": false,
  "horizontalSpacing": 0,
  "isFixedToViewport": false,
  "isFlippedHorizontal": false,
  "isFlippedVertical": false,
  "isLocked": false,
  "isVisible": true,
  "layerListExpandedType": 0,
  "name": "Nav/border",
  "nameIsFixed": false,
  "overrideValues": [
    {
      "_class": "overrideValue",
      "do_objectID": "735A2E71-851E-4C97-89BE-D56DE7671E12",
      "overrideName": "61033FD4-C9E3-4413-B213-62EA79FD358A_symbolID",
      "value": ""
    },
    {
      "_class": "overrideValue",
      "do_objectID": "A4287312-CE4E-4986-B4D7-40BD538A6404",
      "overrideName": "2FE2D8D2-B215-40E1-AF5F-348C661AA953_stringValue",
      "value": "Nav item"
    },
    {
      "_class": "overrideValue",
      "do_objectID": "F9540C91-E37E-4952-AE68-2D8DE6934172",
      "overrideName": "78B1D4B2-78F9-441C-96DA-396FEB74BDD5_symbolID",
      "value": "A0A90D03-F10F-4FC8-BEE1-871107EB10E8"
    }
  ],
  "resizingConstraint": 63,
  "resizingType": 0,
  "rotation": 0,
  "scale": 1,
  "shouldBreakMaskChain": false,
  "style": {
    "_class": "style",
    "do_objectID": "FDF6A039-8A63-4876-89B9-6BA77BA835A7",
    "endMarkerType": 0,
    "miterLimit": 10,
    "startMarkerType": 0,
    "windingRule": 1
  },
  "symbolID": "AEF1F9F4-92B7-4D7D-A13B-EE11838E6707",
  "userInfo": {
    "com.animaapp.stc-sketch-plugin": {
      "kModelPropertiesKey": {
      }
    }
  },
  "verticalSpacing": 0
}