{
  "_class": "symbolInstance",
  "booleanOperation": -1,
  "clippingMaskMode": 0,
  "do_objectID": "08547EE8-B8F6-48C9-A5D6-095753EBDBFC",
  "exportOptions": {
    "_class": "exportOptions",
    "do_objectID": "04F3BB19-197B-4C9A-8B28-410DAE5557EB",
    "exportFormats": [
    ],
    "includedLayerIds": [
    ],
    "layerOptions": 0,
    "shouldTrim": false
  },
  "frame": {
    "_class": "rect",
    "constrainProportions": false,
    "do_objectID": "934AFC04-98BE-4762-8D4E-1ADD21998A51",
    "height": 46.2439024390244,
    "width": 44.49334461798773,
    "x": 129.7722551358007,
    "y": 0
  },
  "hasClippingMask": false,
  "horizontalSpacing": 0,
  "isFixedToViewport": false,
  "isFlippedHorizontal": false,
  "isFlippedVertical": false,
  "isLocked": false,
  "isVisible": true,
  "layerListExpandedType": 0,
  "name": "Date-picker/z.assets/cell-style/default",
  "nameIsFixed": false,
  "overrideValues": [
    {
      "_class": "overrideValue",
      "do_objectID": "EF1AA058-6DC9-430D-AF0D-08CF091F45FE",
      "overrideName": "C752BA20-D4CA-4D86-AAA5-899EB8C5E32F/302F44CB-C5EE-4C5E-8FA1-FEE1784732DA_stringValue",
      "value": "30"
    }
  ],
  "resizingConstraint": 63,
  "resizingType": 0,
  "rotation": 0,
  "scale": 1,
  "shouldBreakMaskChain": false,
  "style": {
    "_class": "style",
    "do_objectID": "1C63B38E-86A8-41D2-82A0-006FAB9FCAB2",
    "endMarkerType": 0,
    "miterLimit": 10,
    "startMarkerType": 0,
    "windingRule": 1
  },
  "symbolID": "65897BEE-1962-4C0F-BB8B-C1AC04E1734D",
  "userInfo": {
    "com.animaapp.stc-sketch-plugin": {
      "kModelPropertiesKey": {
      }
    }
  },
  "verticalSpacing": 0
}